toloka_provider/__init__.py
toloka_provider/hooks/__init__.py
toloka_provider/hooks/toloka.py
toloka_provider/sensors/__init__.py
toloka_provider/sensors/toloka.py
toloka_provider/tasks/__init__.py
toloka_provider/tasks/toloka.py
toloka_provider/utils/__init__.py
toloka_provider/utils/utils.py
airflow_provider_toloka-0.0.8.dist-info/AUTHORS
airflow_provider_toloka-0.0.8.dist-info/LICENSE
airflow_provider_toloka-0.0.8.dist-info/METADATA
airflow_provider_toloka-0.0.8.dist-info/WHEEL
airflow_provider_toloka-0.0.8.dist-info/entry_points.txt
airflow_provider_toloka-0.0.8.dist-info/top_level.txt
airflow_provider_toloka-0.0.8.dist-info/RECORD
