Metadata-Version: 2.1
Name: airflow-provider-toloka
Version: 0.0.8
Summary: A Toloka provider for Apache Airflow
Author: Denis Makarov
Author-email: pocoder@toloka.ai
License: Apache License 2.0
Project-URL: Source, https://github.com/Toloka/airflow-provider-toloka
Classifier: Development Status :: 4 - Beta
Classifier: Framework :: Apache Airflow
Classifier: Framework :: Apache Airflow :: Provider
Classifier: Intended Audience :: Developers
Classifier: Intended Audience :: Science/Research
Classifier: License :: OSI Approved :: Apache Software License
Classifier: Operating System :: OS Independent
Classifier: Programming Language :: Python
Classifier: Programming Language :: Python :: 3
Classifier: Programming Language :: Python :: 3.7
Classifier: Programming Language :: Python :: 3.8
Classifier: Programming Language :: Python :: 3.9
Classifier: Programming Language :: Python :: 3.10
Classifier: Programming Language :: Python :: Implementation :: CPython
Classifier: Topic :: Scientific/Engineering
Classifier: Topic :: Software Development
Classifier: Typing :: Typed
Requires-Python: >=3.7.0
License-File: LICENSE
License-File: AUTHORS
Requires-Dist: apache-airflow (>=2.1.0)
Requires-Dist: toloka-kit (>=1.0.0rc1)
